Metadata-Version: 2.1
Name: scscipy
Version: 0.1
Summary: scscipy
Author-email: applepro285@gmail.com
